gradeiate/__init__.py
gradeiate-1.6.dist-info/METADATA
gradeiate-1.6.dist-info/WHEEL
gradeiate-1.6.dist-info/top_level.txt
gradeiate-1.6.dist-info/RECORD
