Metadata-Version: 2.1
Name: gradeiate
Version: 1.6
Summary: Style your Python application with gradient colors
Author: vington
Author-email: <team@vington.org>
License: Eclipse Public License 2.0
Keywords: gradeiate,Virtual Machine
Classifier: Intended Audience :: Developers
Classifier: Natural Language :: English
Classifier: Programming Language :: Python :: 3
Classifier: Programming Language :: Python :: 3.5
Classifier: Programming Language :: Python :: 3.6
Classifier: Programming Language :: Python :: 3.7
Classifier: Programming Language :: Python :: 3.8
Classifier: Programming Language :: Python :: 3.9
Classifier: Programming Language :: Python :: 3.10
